[{"kod":"0401","organ":"Starosta Aleksandrowski","pow":"aleksandrowski","jP":"KPP w Aleksandrowie Kujawskim","woj":null},
    {"kod":"2001","organ":"Starosta Augustowski","pow":"augustowski","jP":"KPP Augustów","woj":null},
    {"kod":"2801","organ":"Starosta Bartoszycki","pow":"bartoszycki","jP":"KPP w Bartoszycach","woj":null},
    {"kod":"1001","organ":"Starosta Bełchatowski","pow":"bełchatowski","jP":"KPP w Bełchatowie","woj":null},
    {"kod":"2401","organ":"Starosta Będziński","pow":"będziński","jP":"KPP w Będzinie","woj":null},
    {"kod":"0601","organ":"Starosta Bialski","pow":"bialski","jP":"KMP w Białej Podlaskiej","woj":null},
    {"kod":"0661","organ":"Prezydent Miasta Biała Podlaska","pow":"Biała Podlaska","jP":"KMP w Białej Podlaskiej","woj":null},
    {"kod":"1401","organ":"Starosta Białobrzeski","pow":"białobrzeski","jP":"KPP w Białobrzegach","woj":null},
    {"kod":"3201","organ":"Starosta Białogardzki","pow":"białogardzki","jP":"KPP w Białogardzie","woj":null},
    {"kod":"2002","organ":"Starosta Białostocki","pow":"białostocki","jP":"KMP Białystok","woj":null},
    {"kod":"2061","organ":"Prezydent Miasta Bialegostoku","pow":"Białystok","jP":"KMP Białystok","woj":null},
    {"kod":"2003","organ":"Starosta Bielski","pow":"bielski","jP":"KPP Bielsk Podlaski","woj":"podlaskie"},
    {"kod":"2402","organ":"Starosta Bielski","pow":"bielski","jP":"KMP w Bielsku-Białej","woj":"śląskie"},
    {"kod":"2461","organ":"Prewzydent Miasta Bielsko-Białej","pow":"Bielsko-Biała","jP":"KMP w Bielsku-Białej","woj":null},
    {"kod":"2414","organ":"Starosta Bieruńsko-Lędziński","pow":"bieruńsko-lędziński","jP":"KPP w Bieruniu","woj":null},
    {"kod":"0602","organ":"Starosta Biłgorajski","pow":"biłgorajski","jP":"KPP w Biłgoraju","woj":null},
    {"kod":"1201","organ":"Starosta Bocheński","pow":"bocheński","jP":"KPP w Bochni","woj":null},
    {"kod":"0201","organ":"Starosta Boleslawiecki","pow":"bolesławiecki","jP":"KPP w Bolesławcu","woj":null},
    {"kod":"2802","organ":"Starosta Braniewski","pow":"braniewski","jP":"KPP w Braniewie","woj":null},
    {"kod":"0402","organ":"Starosta Brodnicki","pow":"brodnicki","jP":"KPP w Brodnicy","woj":null},
    {"kod":"1601","organ":"Starosta Brzeski","pow":"brzeski","jP":"KPP w Brzegu","woj":"opolskie"},
    {"kod":"1202","organ":"Starosta Brzeski","pow":"brzeski","jP":"KPP w Brzesku","woj":"małopolskie"},
    {"kod":"1021","organ":"Starosta Brzeziński","pow":"brzeziński","jP":"KPP w Brzezinach","woj":null},
    {"kod":"1802","organ":"Starosta Brzozowski","pow":"brzozowski","jP":"KPP w Brzozowie","woj":null},
    {"kod":"2601","organ":"Starosta Buski","pow":"buski","jP":"KPP Busko-Zdrój","woj":null},
    {"kod":"0403","organ":"Starosta Bydgoski","pow":"bydgoski","jP":"KMP w Bydgoszczy","woj":null},
    {"kod":"0461","organ":"Prezydent Miasta Bydgoszczy","pow":"Bydgoszcz","jP":"KMP w Bydgoszczy","woj":null},
    {"kod":"2462","organ":"Prezydent Miasta Bytomia","pow":"Bytom","jP":"KMP w Bytomiu","woj":null},
    {"kod":"2201","organ":"Starosta Bytowski","pow":"bytowski","jP":"KPP w Bytów","woj":null},
    {"kod":"0603","organ":"Starosta Chełmski","pow":"chełmski","jP":"KMP w Chełmie","woj":null},
    {"kod":"0662","organ":"Prezydent Miasta Chełm","pow":"Chełm","jP":"KMP w Chełmie","woj":null},
    {"kod":"3001","organ":"Starosta Chodzieski","pow":"chodzieski","jP":"KPP Chodzież","woj":null},
    {"kod":"2202","organ":"Starosta Chojnicki","pow":"chojnicki","jP":"KPP w Chojnicach","woj":null},
    {"kod":"2463","organ":"Prezydent Miasta Chorzów","pow":"Chorzów","jP":"KMP w Chorzowie","woj":null},
    {"kod":"3202","organ":"Starosta Choszczeński","pow":"choszczeński","jP":"KPP w Choszcznie","woj":null},
    {"kod":"1203","organ":"Starosta Chrzanowski","pow":"chrzanowski","jP":"KPP w Chrzanowie","woj":null},
    {"kod":"1402","organ":"Starosta Ciechanowski","pow":"ciechanowski","jP":"KPP w Ciechanowie","woj":null},
    {"kod":"2403","organ":"Starosta Cieszyński","pow":"cieszyński","jP":"KPP w Cieszynie","woj":null},
    {"kod":"3002","organ":"Starosta Czarnkowsko-Trzcianecki","pow":"czarnkowsko-trzcianecki","jP":"KPP w Czarnkowie","woj":null},
    {"kod":"2404","organ":"Starosta Częstochowski","pow":"częstochowski","jP":"KMP w Częstochowie","woj":null},
    {"kod":"2464","organ":"Prezydent Miasta Częstochowa","pow":"Częstochowa","jP":"KMP w Częstochowie","woj":null},
    {"kod":"2405","organ":"Starosta Gliwicki","pow":"gliwicki","jP":"KMP w Gliwicach","woj":null},
    {"kod":"2466","organ":"Prezydent Miasta Gliwice","pow":"Gliwice","jP":"KMP w Gliwicach","woj":null},
    {"kod":"0203","organ":"Starosta Głogowski","pow":"głogowski","jP":"KPP Głogów","woj":null},
    {"kod":"1602","organ":"Starosta Głubczycki","pow":"głubczycki","jP":"KPP w Głubczycach","woj":null},
    {"kod":"3003","organ":"Starosta Gnieźnieński","pow":"gnieźnieński","jP":"KPP w Gnieźnie","woj":null},
    {"kod":"3204","organ":"Starosta Goleniowski","pow":"goleniowski","jP":"KPP w Goleniowie","woj":null},
    {"kod":"0405","organ":"Starosta Golubsko-Dobrzyński","pow":"Golubsko-dobrzyński","jP":"KPP w Golubiu Dobrzyniu","woj":null},
    {"kod":"2818","organ":"Starosta Gołdapski","pow":"gołdapski","jP":"KPP w Gołdapi","woj":null},
    {"kod":"1205","organ":"Starosta Gorlicki","pow":"gorlicki","jP":"KPP w Gorlicach","woj":null},
    {"kod":"0801","organ":"Starosta Gorzowski","pow":"gorzowski","jP":"KMP w Gorzowie Wlkp.","woj":null},
    {"kod":"0861","organ":"Prezydent Miasta Gorzów Wielkopolski","pow":"Gorzów Wielkopolski","jP":"KMP w Gorzowie Wlkp.","woj":null},
    {"kod":"1404","organ":"Starosta Gostyniński","pow":"gostyniński","jP":"KPP w Gostyninie","woj":null},
    {"kod":"3004","organ":"Starosta Gostyński","pow":"gostyński","jP":"KPP w Gostyniu","woj":null},
    {"kod":"0204","organ":"Starosta Górowski","pow":"górowski","jP":"KPP w Górze","woj":null},
    {"kod":"2004","organ":"Starosta Grajewski","pow":"grajewski","jP":"KPP w Grajewie","woj":null},
    {"kod":"1405","organ":"Starosta Grodziski","pow":"grodziski","jP":"KPP w Grodzisku Mazowieckim","woj":"mazowieckie"},
    {"kod":"3005","organ":"Starosta Grodziski","pow":"grodziski","jP":"KPP w Grodzisku Wielkopolskim","woj":"wielkopolskie"},
    {"kod":"1406","organ":"Starosta Grójecki","pow":"grójecki","jP":"KPP w Grójcu","woj":null},
    {"kod":"0406","organ":"Starosta Grudziądzki","pow":"grudziądzki","jP":"KMP w Grudziądzu","woj":null},
    {"kod":"0462","organ":"Prezydent Miasta Grudziądza","pow":"Grudziądz","jP":"KMP w Grudziądzu","woj":null},
    {"kod":"3205","organ":"Starosta Gryficki","pow":"gryficki","jP":"KPP w Gryficach","woj":null},
    {"kod":"3206","organ":"Starosta Gryfiński","pow":"gryfiński","jP":"KPP w Gryfinie","woj":null},
    {"kod":"2005","organ":"Starosta Hajnowski","pow":"hajnowski","jP":"KPP w Hajnówce","woj":null},
    {"kod":"0604","organ":"Starosta Hrubieszowski","pow":"hrubieszowski","jP":"KPP w Hrubieszowie","woj":null},
    {"kod":"2807","organ":"Starosta Iławski","pow":"iławski","jP":"KPP W Iławie","woj":null},
    {"kod":"0407","organ":"Starosta Inowrocławski","pow":"inowrocławski","jP":"KPP w Inowrocławiu","woj":null},
    {"kod":"0605","organ":"Starosta Janowski","pow":"janowski","jP":"KPP w Janowie Lubelskim","woj":null},
    {"kod":"3006","organ":"Starosta Jarociński","pow":"jarociński","jP":"KPP w Jarocinie","woj":null},
    {"kod":"1804","organ":"Starosta Jarosławski","pow":"jarosławski","jP":"KPP w Jarosławiu","woj":null},
    {"kod":"1805","organ":"Starosta Jasielski","pow":"jasielski","jP":"KPP w Jaśle","woj":null},
    {"kod":"2467","organ":"Prezydent Miasta Jastrzębie Zdrój","pow":"Jastrzębie-Zdrój","jP":"KMP w Jastrzębiu Zdroju","woj":null},
    {"kod":"0205","organ":"Starosta Jaworski","pow":"jaworski","jP":"KPP w Jaworze","woj":null},
    {"kod":"2468","organ":"Prezydent Miasta Jaworzna","pow":"Jaworzno","jP":"KMP w Jaworznie","woj":null},
    {"kod":"0206","organ":"Starosta Jeleniogórski","pow":"jeleniogórski","jP":"KMP w Jeleniej Górze","woj":null},
    {"kod":"0261","organ":"Prezydent Miasta Jeleniej Góry","pow":"Jelenia Góra","jP":"KMP w Jeleniej Górze","woj":null},
    {"kod":"2602","organ":"Starosta Jędrzejowski","pow":"jędrzejowski","jP":"KPP w Jędrzejowie","woj":null},
    {"kod":"3007","organ":"Starosta Kaliski","pow":"kaliski","jP":"KMP w Kaliszu","woj":null},
    {"kod":"3061","organ":"Prezydent Miasta Kalisza","pow":"Kalisz","jP":"KMP w Kaliszu","woj":null},
    {"kod":"0207","organ":"Starosta Kamiennogórski","pow":"kamiennogórski","jP":"KPP w Kamiennej Górze","woj":null},
    {"kod":"3207","organ":"Starosta Kamieński","pow":"kamieński","jP":"KPP w Kamieniu Pomorskim","woj":null},
    {"kod":"2205","organ":"Starosta Kartuski","pow":"kartuski","jP":"KPP w Kartuzach","woj":null},
    {"kod":"2469","organ":"Prezydent Miasta Katowice","pow":"Katowice","jP":"KMP w Katowicach","woj":null},
    {"kod":"2603","organ":"Starosta Kazimierski","pow":"kazimierski","jP":"KPP Kazimierza Wielka","woj":null},
    {"kod":"1603","organ":"Starosta Kędzierzyńsko-Kozielski","pow":"kędzierzyńsko-kozielski","jP":"KPP w Kędzierzynie - Koźlu","woj":null},
    {"kod":"3008","organ":"Starosta Kępiński","pow":"kępiński","jP":"KPP w Kępnie","woj":null},
    {"kod":"2808","organ":"Starosta Kętrzyński","pow":"kętrzyński","jP":"KPP w Kętrzynie","woj":null},
    {"kod":"2604","organ":"Starosta Kielecki","pow":"kielecki","jP":"KMP w Kielcach","woj":null},
    {"kod":"2661","organ":"Prezydent Miasta Kielce","pow":"Kielce","jP":"KMP w Kielcach","woj":null},
    {"kod":"1604","organ":"Starosta Kluczborski","pow":"kluczborski","jP":"KPP w Kluczborku","woj":null},
    {"kod":"2406","organ":"Starosta Kłobucki","pow":"kłobucki","jP":"KPP w Kłobucku","woj":null},
    {"kod":"0208","organ":"Starosta Kłodzki","pow":"kłodzki","jP":"KPP w Kłodzku","woj":null},
    {"kod":"1806","organ":"Starosta Kolbuszowski","pow":"kolbuszowski","jP":"KPP w Kolbuszowej","woj":null},
    {"kod":"2006","organ":"Starosta Kolneński","pow":"kolneński","jP":"KPP w Kolnie","woj":null},
    {"kod":"3009","organ":"Starosta Kolski","pow":"kolski","jP":"KPP w Kole","woj":null},
    {"kod":"3208","organ":"Starosta Kołobrzeski","pow":"kołobrzeski","jP":"KPP w Kołobrzegu","woj":null},
    {"kod":"3009","organ":"Starosta Koniński","pow":"koniński","jP":"KMP w Koninie","woj":null},
    {"kod":"3062","organ":"Prezydent Miasta Konina","pow":"Konin","jP":"KMP w Koninie","woj":null},
    {"kod":"2605","organ":"Starosta Konecki","pow":"konecki","jP":"KPP w Końskich","woj":null},
    {"kod":"3209","organ":"Starosta Koszaliński","pow":"koszaliński","jP":"KMP w Koszalinie","woj":null},
    {"kod":"3261","organ":"Prezydent Miasta Koszalina","pow":"Koszalin","jP":"KMP w Koszalinie","woj":null},
    {"kod":"3011","organ":"Starosta Kościański","pow":"kościański","jP":"KPP w Kościanie","woj":null},
    {"kod":"2206","organ":"Starosta Kościerski","pow":"kościerski","jP":"KPP w Kościerzynie","woj":null},
    {"kod":"1407","organ":"Starosta Kozienicki","pow":"kozienicki","jP":"KPP w Kozienicach","woj":null},
    {"kod":"1206","organ":"Starosta Krakowski","pow":"krakowski","jP":"KPP w Krakowie","woj":null},
    {"kod":"1261","organ":"Prezydent Miasta Krakowa","pow":"Kraków","jP":"KMP w Krakowie","woj":null},
    {"kod":"1605","organ":"Starosta Krapkowicki","pow":"krapkowicki","jP":"KPP w Krapkowicach","woj":null},
    {"kod":"0606","organ":"Starosta Krasnostawski","pow":"krasnostawski","jP":"KPP w Krasnymstawie","woj":null},
    {"kod":"0607","organ":"Starosta Kraśnicki","pow":"kraśnicki","jP":"KPP w Kraśniku","woj":null},
    {"kod":"1807","organ":"Starosta Krośnieński","pow":"krośnieński","jP":"KMP w Krośnie","woj":"podkarpackie"},
    {"kod":"1861","organ":"Prezydent Miasta Krosna","pow":"Krosno","jP":"KMP w Krośnie","woj":null},
    {"kod":"0802","organ":"Starosta Krośnieński","pow":"krośnieński","jP":"KPP w Krośnie Odrzańskim","woj":"lubuskie"},
    {"kod":"3012","organ":"Starosta Krotoszyński","pow":"krotoszyński","jP":"KPP w Krotoszynie","woj":null},
    {"kod":"1002","organ":"Starosta Kutnowski","pow":"kutnowski","jP":"KPP w Kutnie","woj":null},
    {"kod":"2207","organ":"Starosta Kwidzyński","pow":"kwidzyński","jP":"KPP w Kwidzynie","woj":null},
    {"kod":"1408","organ":"Starosta Legionowski","pow":"legionowski","jP":"KPP w Legionowie","woj":null},
    {"kod":"0209","organ":"Starosta Legnicki","pow":"legnicki","jP":"KMP w Legnicy","woj":null},
    {"kod":"0262","organ":"Prezydent Miasta Legnica","pow":"Legnica","jP":"KMP w Legnicy","woj":null},
    {"kod":"1821","organ":"Starosta Leski","pow":"leski","jP":"KPP w Lesku","woj":null},
    {"kod":"3013","organ":"Starosta Leszczyński","pow":"leszczyński","jP":"KMP w Lesznie","woj":null},
    {"kod":"3063","organ":"Prezydent Miasta Leszna","pow":"Leszno","jP":"KMP w Lesznie","woj":null},
    {"kod":"1808","organ":"Starosta Leżajski","pow":"leżajski","jP":"KPP w Leżajsku","woj":null},
    {"kod":"2208","organ":"Starosta Lęborski","pow":"lęborski","jP":"KPP w Lęborku","woj":null},
    {"kod":"2809","organ":"Starosta Lidzbarski","pow":"lidzbarski","jP":"KPP w Lidzbarku Warmińskim","woj":null},
    {"kod":"1207","organ":"Starosta Limanowski","pow":"limanowski","jP":"KPP w Limanowej","woj":null},
    {"kod":"0408","organ":"Starosta Lipnowski","pow":"lipnowski","jP":"KPP w Lipnie","woj":null},
    {"kod":"1409","organ":"Starosta Lipski","pow":"lipski","jP":"KPP w Lipsku","woj":null},
    {"kod":"1809","organ":"Starosta Lubaczowski","pow":"lubaczowski","jP":"KPP w Lubaczowie","woj":null},
    {"kod":"0210","organ":"Starosta Lubański","pow":"lubański","jP":"KPP w Lubaniu","woj":null},
    {"kod":"0608","organ":"Starosta Lubartowski","pow":"lubartowski","jP":"KPP w Lubartowie","woj":null},
    {"kod":"0211","organ":"Starosta Lubiński","pow":"lubiński","jP":"KPP w Lubinie","woj":null},
    {"kod":"0609","organ":"Starosta Lubelski","pow":"lubelski","jP":"KMP w Lublinie","woj":null},
    {"kod":"0663","organ":"Prezydent Miasta Lublin","pow":"Lublin","jP":"KMP w Lublinie","woj":null},
    {"kod":"2407","organ":"Starosta Lubliniecki","pow":"lubliniecki","jP":"KPP w Lublińcu","woj":null},
    {"kod":"0212","organ":"Starosta Lwówecki","pow":"lwówecki","jP":"KPP w Lwówku Śląskim","woj":null},
    {"kod":"1810","organ":"Starosta Łańcucki","pow":"łańcucki","jP":"KPP w Łańcucie","woj":null},
    {"kod":"1003","organ":"Starosta Łaski","pow":"łaski","jP":"KPP w Łasku","woj":null},
    {"kod":"0610","organ":"Starosta Łęczyński","pow":"łęczyński","jP":"KPP w Łęcznej","woj":null},
    {"kod":"1004","organ":"Starosta Łęczycki","pow":"łęczycki","jP":"KPP w Łęczycy","woj":null},
    {"kod":"3218","organ":"Starosta Łobeski","pow":"łobeski","jP":"KPP w Łobzie","woj":null},
    {"kod":"2007","organ":"Starosta Łomżyński","pow":"łomżyński","jP":"KPM w Łomży","woj":null},
    {"kod":"2062","organ":"Prezydent Miasta Łomży","pow":"Łomża","jP":"KPM w Łomży","woj":null},
    {"kod":"1410","organ":"Starosta Łosicki","pow":"łosicki","jP":"KPP w Łosicach","woj":null},
    {"kod":"1005","organ":"Starosta Łowicki","pow":"łowicki","jP":"KPP w Łowiczu","woj":null},
    {"kod":"1006","organ":"Starosta Łódzki Wschodni","pow":"łódzki wschodni","jP":"KPP Łódź-Wschód","woj":null},
    {"kod":"1061","organ":"Prezydent Miasta Łodzi","pow":"Łódź","jP":"KMP w Łodzi","woj":null},
    {"kod":"0611","organ":"Starosta Łukowski","pow":"łukowski","jP":"KPP w Łukowie","woj":null},
    {"kod":"1411","organ":"Starosta Makowski","pow":"makowski","jP":"KPP w Makowie Mazowieckim","woj":null},
    {"kod":"2209","organ":"Starosta Malborski","pow":"malborski","jP":"KPP w Malborku","woj":null},
    {"kod":"1208","organ":"Starosta Miechowski","pow":"miechowski","jP":"KPP w Miechowie","woj":null},
    {"kod":"1811","organ":"Starosta Mielecki","pow":"mielecki","jP":"KPP w Mielcu","woj":null},
    {"kod":"3014","organ":"Starosta Międzychodzki","pow":"międzychodzki","jP":"KPP w Międzychodzie","woj":null},
    {"kod":"0803","organ":"Starosta Międzyrzecki","pow":"międzyrzecki","jP":"KPP w Międzyrzeczu","woj":null},
    {"kod":"2408","organ":"Starosta Mikołowski","pow":"mikołowski","jP":"KPP w Mikołowie","woj":null},
    {"kod":"0213","organ":"Starosta Milicki","pow":"milicki","jP":"KPP w Miliczu","woj":null},
    {"kod":"1412","organ":"Starosta Miński","pow":"miński","jP":"KPP w Mińsku Mazowieckim","woj":null},
    {"kod":"1413","organ":"Starosta Mławski","pow":"mławski","jP":"KPP w Mławie","woj":null},
    {"kod":"0409","organ":"Starosta Mogileński","pow":"mogileński","jP":"KPP w Mogilnie","woj":null},
    {"kod":"2008","organ":"Starosta Moniecki","pow":"moniecki","jP":"KPP w Mońkach","woj":null},
    {"kod":"2810","organ":"Starosta Mrągowski","pow":"mrągowski","jP":"KPP w Mrągowie","woj":null},
    {"kod":"2470","organ":"Prezydent Miasta Mysłowice","pow":"Mysłowice","jP":"KMP w Mysłowicach","woj":null},
    {"kod":"2409","organ":"Starosta Myszkowski","pow":"myszkowski","jP":"KPP w Myszkowie","woj":null},
    {"kod":"1209","organ":"Starosta Myślenicki","pow":"myślenicki","jP":"KPP w Myślenicach","woj":null},
    {"kod":"3210","organ":"Starosta Myśliborski","pow":"myśliborski","jP":"KPP w Myśliborzu","woj":null},
    {"kod":"0410","organ":"Starosta Nakielski","pow":"nakielski","jP":"KPP w Nakle nad Notecią","woj":null},
    {"kod":"1606","organ":"Starosta Namysłowski","pow":"namysłowski","jP":"KPP w Namysłowie","woj":null},
    {"kod":"2811","organ":"Starosta Nidzicki","pow":"nidzicki","jP":"KPP w Nidzicy","woj":null},
    {"kod":"1812","organ":"Starosta Niżański","pow":"niżański","jP":"KPP w Nisku","woj":null},
    {"kod":"0804","organ":"Starosta Nowosolski","pow":"nowosolski","jP":"KPP w Nowej Soli","woj":null},
    {"kod":"2812","organ":"Starosta Nowomiejski","pow":"nowomiejski","jP":"KPP w Nowym Mieście Lubawskim","woj":null},
    {"kod":"2210","organ":"Starosta Nowodworski","pow":"nowodworski","jP":"KPP w Nowym Dworze Gdańskim","woj":"pomorskie"},
    {"kod":"1414","organ":"Starosta Nowodworski","pow":"nowodworski","jP":"KPP w Nowym Dworze Mazowieckim","woj":"mazowieckie"},
    {"kod":"1210","organ":"Starosta Nowosądecki","pow":"nowosądecki","jP":"KMP w Nowym Sączu","woj":null},
    {"kod":"1262","organ":"Prezydent Miasta Nowy Sącz","pow":"Nowy Sącz","jP":"KMP w Nowym Sączu","woj":null},
    {"kod":"1211","organ":"Starosta Nowotarski","pow":"nowotarski","jP":"KPP w Nowym Targu","woj":null},
    {"kod":"3015","organ":"Starosta Nowotomyski","pow":"nowotomyski","jP":"KPP w Nowym Tomyślu","woj":null},
    {"kod":"1607","organ":"Starosta Nyski","pow":"nyski","jP":"KPP w Nysie","woj":null},
    {"kod":"3016","organ":"Starosta Obornicki","pow":"obornicki","jP":"KPP w Obornikach","woj":null},
    {"kod":"2813","organ":"Starosta Olecki","pow":"olecki","jP":"KPP w Olecku","woj":null},
    {"kod":"1608","organ":"Starosta Oleski","pow":"oleski","jP":"KPP w Oleśnie","woj":null},
    {"kod":"0214","organ":"Starosta Oleśnicki","pow":"oleśnicki","jP":"KPP w Oleśnicy","woj":null},
    {"kod":"1212","organ":"Starosta Olkuski","pow":"olkuski","jP":"KPP w Olkuszu","woj":null},
    {"kod":"2814","organ":"Starosta Olsztyński","pow":"olsztyński","jP":"KMP w Olsztynie","woj":null},
    {"kod":"2862","organ":"Prezydent Miasta Olsztyna","pow":"Olsztyn","jP":"KMP w Olsztynie","woj":null},
    {"kod":"0215","organ":"Starosta Oławski","pow":"oławski","jP":"KPP w Oławie","woj":null},
    {"kod":"2606","organ":"Starosta Opatowski","pow":"opatowski","jP":"KPP w Opatowie","woj":null},
    {"kod":"1007","organ":"Starosta Opoczyński","pow":"opoczyński","jP":"KPP w Opocznie","woj":null},
    {"kod":"1609","organ":"Starosta Opolski","pow":"opolski","jP":"KMP w Opolu","woj":"opolskie"},
    {"kod":"1661","organ":"Prezydent Miasta Opola","pow":"Opola","jP":"KMP w Opolu","woj":null},
    {"kod":"0612","organ":"Starosta Opolski","pow":"opolski","jP":"KPP w Opolu Lubelskim","woj":"lubelskie"},
    {"kod":"1415","organ":"Starosta Ostrołęcki","pow":"ostrołęcki","jP":"KMP w Ostrołęce","woj":null},
    {"kod":"1461","organ":"Prezydent Miasta Ostrołęka","pow":"Ostrołęka","jP":"KMP w Ostrołęce","woj":null},
    {"kod":"2607","organ":"Starosta Ostrowiecki","pow":"ostrowiecki","jP":"KPP w Ostrowcu Świętokrzyskim","woj":null},
    {"kod":"2815","organ":"Starosta Ostródzki","pow":"ostródzki","jP":"KPP w Ostródzie","woj":null},
    {"kod":"1416","organ":"Starosta Ostrowski","pow":"ostrowski","jP":"KPP w Ostrowi Mazowieckiej","woj":"mazowieckie"},
    {"kod":"3017","organ":"Starosta Ostrowski","pow":"ostrowski","jP":"KPP w Ostrowie Wielkopolskim","woj":"wielkopolskie"},
    {"kod":"3018","organ":"Starosta Ostrzeszowski","pow":"ostrzeszowski","jP":"KPP Ostrzeszów","woj":null},
    {"kod":"1213","organ":"Starosta Oświęcimski","pow":"oświęcimski","jP":"KPP w Oświęcimiu","woj":null},
    {"kod":"1417","organ":"Starosta Otwocki","pow":"otwocki","jP":"KPP w Otwocku","woj":null},
    {"kod":"1008","organ":"Starosta Pabianicki","pow":"pabianicki","jP":"KPP w Pabianicach","woj":null},
    {"kod":"1009","organ":"Starosta Pajęczański","pow":"pajęczański","jP":"KPP w Pajęcznie","woj":null},
    {"kod":"0613","organ":"Starosta Parczewski","pow":"parczewski","jP":"KPP w Parczewie","woj":null},
    {"kod":"1418","organ":"Starosta Piaseczyński","pow":"piaseczyński","jP":"KPP w Piasecznie","woj":null},
    {"kod":"2471","organ":"Prezydent Miasta Piekary Śląskie","pow":"Piekary Śląskie","jP":"KMP w Piekarach Śląskich","woj":null},
    {"kod":"3019","organ":"Starosta Pilski","pow":"pilski","jP":"KPP Piła","woj":null},
    {"kod":"2608","organ":"Starosta Pińczowski","pow":"pińczowski","jP":"KPP w Pińczowie","woj":null},
    {"kod":"1010","organ":"Starosta Piotrkowski","pow":"piotrkowski","jP":"KMP w Piotrkowie Trybunalskim","woj":null},
    {"kod":"1062","organ":"Prezydent Miasta Piotrków Trybunalski","pow":"Piotrków Trybunalski","jP":"KMP w Piotrkowie Trybunalskim","woj":null},
    {"kod":"2816","organ":"Starosta Piski","pow":"piski","jP":"KPP w Piszu","woj":null},
    {"kod":"3020","organ":"Starosta Pleszewski","pow":"pleszewski","jP":"KPP w Pleszewie","woj":null},
    {"kod":"1419","organ":"Starosta Płocki","pow":"płocki","jP":"KMP w Płocku","woj":null},
    {"kod":"1462","organ":"Prezydent Miasta Płocka","pow":"Płock","jP":"KMP w Płocku","woj":null},
    {"kod":"1420","organ":"Starosta Płoński","pow":"płoński","jP":"KPP w Płońsku","woj":null},
    {"kod":"1011","organ":"Starosta Poddębicki","pow":"poddębicki","jP":"KPP w Poddębicach","woj":null},
    {"kod":"3211","organ":"Starosta Policki","pow":"policki","jP":"KPP w Policach","woj":null},
    {"kod":"0216","organ":"Starosta Polkowicki","pow":"polkowicki","jP":"KPP w Polkowicach","woj":null},
    {"kod":"3021","organ":"Starosta Poznański","pow":"poznański","jP":"KMP w Poznaniu","woj":null},
    {"kod":"3064","organ":"Prezydent Miasta Poznania","pow":"Poznań","jP":"KMP w Poznaniu","woj":null},
    {"kod":"1214","organ":"Starosta Proszowicki","pow":"proszowicki","jP":"KPP w Proszowicach","woj":null},
    {"kod":"1610","organ":"Starosta Prudnicki","pow":"prudnicki","jP":"KPP w Prudniku","woj":null},
    {"kod":"2204","organ":"Starosta Gdański","pow":"gdański","jP":"KPP w Pruszczu Gdańskim","woj":null},
    {"kod":"1421","organ":"Starosta Pruszkowski","pow":"pruszkowski","jP":"KPP w Pruszkowie","woj":null},
    {"kod":"1422","organ":"Starosta Przasnyski","pow":"przasnyski","jP":"KPP w Przasnyszu","woj":null},
    {"kod":"1813","organ":"Starosta Przemyski","pow":"przemyski","jP":"KMP w Przemyślu","woj":null},
    {"kod":"1862","organ":"Prezydent Miasta Przemyśla","pow":"Przemyśl","jP":"KMP w Przemyślu","woj":null},
    {"kod":"1814","organ":"Starosta Przeworski","pow":"przeworski","jP":"KPP w Przeworsku","woj":null},
    {"kod":"1423","organ":"Starosta Przysuski","pow":"przysuski","jP":"KPP w Przysusze","woj":null},
    {"kod":"2410","organ":"Starosta Pszczyński","pow":"pszczyński","jP":"KPP w Pszczynie","woj":null},
    {"kod":"2211","organ":"Starosta Pucki","pow":"pucki","jP":"KPP w Pucku","woj":null},
    {"kod":"0614","organ":"Starosta Puławski","pow":"puławski","jP":"KPP w Puławach","woj":null},
    {"kod":"1424","organ":"Starosta Pułtuski","pow":"pułtuski","jP":"KPP w Pułtusku","woj":null},
    {"kod":"3212","organ":"Starosta Pyrzycki","pow":"pyrzycki","jP":"KPP w Pyrzycach","woj":null},
    {"kod":"2411","organ":"Starosta Raciborski","pow":"raciborski","jP":"KPP w Raciborzu","woj":null},
    {"kod":"1425","organ":"Starosta Radomski","pow":"radomski","jP":"KMP W Radomiu","woj":null},
    {"kod":"1463","organ":"Prezydent Miasta Radomia","pow":"Radom","jP":"KMP W Radomiu","woj":null},
    {"kod":"1012","organ":"Starosta Radomszczański","pow":"radomszczański","jP":"KPP w Radomsku","woj":null},
    {"kod":"0411","organ":"Starosta Radziejowski","pow":"radziejowski","jP":"KPP w Radziejowie","woj":null},
    {"kod":"0615","organ":"Starosta Radzyński","pow":"radzyński","jP":"KPP w Radzyniu Podlaskim","woj":null},
    {"kod":"1013","organ":"Starosta Rawski","pow":"rawski","jP":"KPP w Rawie Mazowieckiej","woj":null},
    {"kod":"3022","organ":"Starosta Rawicki","pow":"rawicki","jP":"KPP w Rawiczu","woj":null},
    {"kod":"1815","organ":"Starosta Ropczycko-Sędziszowski","pow":"ropczycko-sędziszowski","jP":"KPP w Ropczycach","woj":null},
    {"kod":"2472","organ":"Prezydent Miasta Ruda Śląska","pow":"Ruda Śląska","jP":"KMP w Rudzie Śląskiej","woj":null},
    {"kod":"2412","organ":"Starosta Rybnicki","pow":"rybnicki","jP":"KMP w Rybniku","woj":null},
    {"kod":"2473","organ":"Prezydent Miasta Rybnika","pow":"Rybnik","jP":"KMP w Rybniku","woj":null},
    {"kod":"0616","organ":"Starosta Rycki","pow":"rycki","jP":"KPP w Rykach","woj":null},
    {"kod":"0412","organ":"Starosta Rypiński","pow":"rypiński","jP":"KPP w Rypinie","woj":null},
    {"kod":"1816","organ":"Starosta Rzeszowski","pow":"rzeszowski","jP":"KMP w Rzeszowie","woj":null},
    {"kod":"1863","organ":"Prezydent Miasta Rzeszowa","pow":"Rzeszów","jP":"KMP w Rzeszowie","woj":null},
    {"kod":"2609","organ":"Starosta Sandomierski","pow":"sandomierski","jP":"KPP w Sandomierzu","woj":null},
    {"kod":"1817","organ":"Starosta Sanocki","pow":"sanocki","jP":"KPP w Sanoku","woj":null},
    {"kod":"2009","organ":"Starosta Sejneński","pow":"sejneński","jP":"KPP w Sejnach","woj":null},
    {"kod":"0413","organ":"Starosta Sępoleński","pow":"sępoleński","jP":"KPP w Sępólnie Krajeńskim","woj":null},
    {"kod":"1426","organ":"Starosta Siedlecki","pow":"siedlecki","jP":"KMP w Siedlcach","woj":null},
    {"kod":"1464","organ":"Prezydent Miasta Siedlce","pow":"Siedlce","jP":"KMP w Siedlcach","woj":null},
    {"kod":"2474","organ":"Prezydent Miasta Siemianowice Śląskie","pow":"Siemianowice Śląski","jP":"KMP w Siemianowicach Śląskich","woj":null},
    {"kod":"2010","organ":"Starosta Siemiatycki","pow":"siemiatycki","jP":"KPP w Siemiatyczach","woj":null},
    {"kod":"1014","organ":"Starosta Sieradzki","pow":"sieradzki","jP":"KPP w Sieradzu","woj":null},
    {"kod":"1427","organ":"Starosta Sierpecki","pow":"sierpecki","jP":"KPP w Sierpcu","woj":null},
    {"kod":"2610","organ":"Starosta Skarżyski","pow":"skarżyski","jP":"KPP w Skarżysku-Kamiennej","woj":null},
    {"kod":"1015","organ":"Starosta Skierniewicki","pow":"skierniewicki","jP":"KMP w Skierniewicach","woj":null},
    {"kod":"1063","organ":"Prezydent Miasta Skierniewice","pow":"Skierniewice","jP":"KMP w Skierniewicach","woj":null},
    {"kod":"3213","organ":"Starosta Sławieński","pow":"sławieński","jP":"KPP w Sławnie","woj":null},
    {"kod":"0805","organ":"Starosta Słubicki","pow":"słubicki","jP":"KPP w Słubicach","woj":null},
    {"kod":"3023","organ":"Starosta Słupecki","pow":"słupecki","jP":"KPP w Słupcy","woj":null},
    {"kod":"2212","organ":"Starosta Słupski","pow":"słupski","jP":"KMP w Słupsku","woj":null},
    {"kod":"2263","organ":"Prezydent Miasta Słupska","pow":"Słupsk","jP":"KMP w Słupsku","woj":null},
    {"kod":"1428","organ":"Starosta Sochaczewski","pow":"sochaczewski","jP":"KPP w Sochaczewie ","woj":null},
    {"kod":"1429","organ":"Starosta Sokołowski","pow":"sokołowski","jP":"KPP w Sokołowie Podlaskim","woj":null},
    {"kod":"2011","organ":"Starosta Sokólski","pow":"sokólski","jP":"KPP w Sokółce","woj":null},
    {"kod":"2264","organ":"Prezydent Miasta Sopotu","pow":"Sopot","jP":"KMP w Sopocie","woj":null},
    {"kod":"2475","organ":"Prezydent Miasta Sosnowiec","pow":"Sosnowiec","jP":"KMP w Sosnowcu","woj":null},
    {"kod":"1818","organ":"Starosta Stalowowolski","pow":"stalowowolski","jP":"KPP w Stalowej Woli","woj":null},
    {"kod":"2611","organ":"Starosta Starachowicki","pow":"starachowicki","jP":"KPP w Starachowicach","woj":null},
    {"kod":"3214","organ":"Starosta Stargardzki","pow":"stargardzki","jP":"KPP w Stargardzie","woj":null},
    {"kod":"2213","organ":"Starosta Starogardzki","pow":"starogardzki","jP":"KPP w Starogardzie Gdańskim","woj":null},
    {"kod":"2612","organ":"Starosta Staszowski","pow":"staszowski","jP":"KPP w Staszowie","woj":null},
    {"kod":"0806","organ":"Starosta Strzelecko-Drezdenecki","pow":"strzelecko-drezdenecki","jP":"KPP w Strzelcach Krajeńskich","woj":null},
    {"kod":"1611","organ":"Starosta Strzelecki","pow":"strzelecki","jP":"KPP w Strzelcach Opolskich","woj":null},
    {"kod":"0217","organ":"Starosta Strzeliński","pow":"strzeliński","jP":"KPP Strzelin","woj":null},
    {"kod":"1819","organ":"Starosta Strzyżowski","pow":"strzyżowski","jP":"KPP w Strzyżowie","woj":null},
    {"kod":"1215","organ":"Starosta Suski","pow":"suski","jP":"KPP w Suchej Beskidzkiej","woj":null},
    {"kod":"0807","organ":"Starosta Sulęciński","pow":"sulęciński","jP":"KPP w Sulęcinie","woj":null},
    {"kod":"2012","organ":"Starosta Suwalski","pow":"suwalski","jP":"KMP w Suwałkach","woj":null},
    {"kod":"2063","organ":"Prezydent Miasta Suwałki","pow":"Suwałki","jP":"KMP w Suwałkach","woj":null},
    {"kod":"3024","organ":"Starosta Szamotulski","pow":"szamotulski","jP":"KPP w Szamotułach","woj":null},
    {"kod":"3262","organ":"Prezydent Miasta Szczecina","pow":"Szczecin","jP":"KMP w Szczecinie","woj":null},
    {"kod":"3215","organ":"Starosta Szczecinecki","pow":"szczecinecki","jP":"KPP w Szczecinku","woj":null},
    {"kod":"2817","organ":"Starosta Szczycieński","pow":"szczycieński","jP":"KPP w Szczytnie","woj":null},
    {"kod":"2216","organ":"Starosta Sztumski","pow":"sztumski","jP":"KPP w Sztumie","woj":null},
    {"kod":"1430","organ":"Starosta Szydłowiecki","pow":"szydłowiecki","jP":"KPP w Szydłowcu","woj":null},
    {"kod":"3026","organ":"Starosta Śremski","pow":"śremski","jP":"KPP w Śremie","woj":null},
    {"kod":"0218","organ":"Starosta Średzki","pow":"średzki","jP":"KPP Środa Śląska","woj":"dolnośląskie"},
    {"kod":"3025","organ":"Starosta Średzki","pow":"średzki","jP":"KPP w Środzie Wlkp","woj":"wielkopolskie"},
    {"kod":"0219","organ":"Starosta Świdnicki","pow":"świdnicki","jP":"KPP w Świdnicy","woj":"dolnośląskie"},
    {"kod":"0617","organ":"Starosta Świdnicki","pow":"świdnicki","jP":"KPP w Świdniku","woj":"lubelskie"},
    {"kod":"3216","organ":"Starosta Świdwiński","pow":"świdwiński","jP":"KPP w Świdwinie","woj":null},
    {"kod":"0808","organ":"Starosta Świebodziński","pow":"świebodziński","jP":"KPP w Świebodzinie","woj":null},
    {"kod":"0414","organ":"Starosta Świecki","pow":"świecki","jP":"KPP w Świeciu","woj":null},
    {"kod":"2476","organ":"Prezydent Miasta Świętochłowice","pow":"Świętochłowice","jP":"KMP w Świętochłowicach","woj":null},
    {"kod":"3263","organ":"Prezydent Miasta Świnoujścia","pow":"Świnoujście","jP":"KMP w Świnoujściu","woj":null},
    {"kod":"1820","organ":"Starosta Tarnobrzeski","pow":"tarnobrzeski","jP":"KMP w Tarnobrzegu","woj":null},
    {"kod":"1864","organ":"Prezydent Miasta Tarnobrzega","pow":"Tarnobrzeg","jP":"KMP w Tarnobrzegu","woj":null},
    {"kod":"2413","organ":"Starosta Tarnogórski","pow":"tarnogórski","jP":"KPP w Tarnowskich Górach","woj":null},
    {"kod":"1216","organ":"Starosta Tarnowski","pow":"tarnowski","jP":"KMP w Tarnowie","woj":null},
    {"kod":"1263","organ":"Prezydent Miasta Tarnowa","pow":"Tarnów","jP":"KMP w Tarnowie","woj":null},
    {"kod":"2214","organ":"Starosta Tczewski","pow":"tczewski","jP":"KPP w Tczewie","woj":null},
    {"kod":"0618","organ":"Starosta Tomaszowski","pow":"tomaszowski","jP":"KPP w Tomaszowie Lubelskim","woj":"lubelskie"},
    {"kod":"1016","organ":"Starosta Tomaszowski","pow":"tomaszowski","jP":"KPP w Tomaszowie Mazowieckim","woj":"łódzkie"},
    {"kod":"0415","organ":"Starosta Toruński","pow":"toruński","jP":"KMP w Toruniu","woj":null},
    {"kod":"0463","organ":"Prezydent Miasta Torunia","pow":"Toruń","jP":"KMP w Toruniu","woj":null},
    {"kod":"0220","organ":"Starosta Trzebnicki","pow":"trzebnicki","jP":"KPP w Trzebnicy","woj":null},
    {"kod":"0416","organ":"Starosta Tucholski","pow":"tucholski","jP":"KPP w Tucholi","woj":null},
    {"kod":"3027","organ":"Starosta Turecki","pow":"turecki","jP":"KPP w Turku","woj":null},
    {"kod":"2477","organ":"Prezydent Miasta Tychy","pow":"Tychy","jP":"KMP w Tychach","woj":null},
    {"kod":"1801","organ":"Starosta Bieszczadzki","pow":"bieszczadzki","jP":"KPP w Ustrzykach Dolnych","woj":null},
    {"kod":"1218","organ":"Starosta Wadowicki","pow":"wadowicki","jP":"KPP w Wadowicach","woj":null},
    {"kod":"0221","organ":"Starosta Wałbrzyski","pow":"wałbrzyski","jP":"KMP Wałbrzych","woj":null},
    {"kod":"0265","organ":"Prezydent Miasta Wałbrzych","pow":"Wałbrzych","jP":"KMP Wałbrzych","woj":null},
    {"kod":"3217","organ":"Starosta Wałecki","pow":"wałecki","jP":"KPP w Wałczu","woj":null},
    {"kod":"1432","organ":"Starosta Warszawski Zachodni","pow":"warszawski zachodni","jP":"KP w Ożarowie Mazowieckim","woj":null},
    {"kod":"1465","organ":"Prezydent Miasta Stołecznego Warszawa","pow":"Warszawa","jP":"Komenda Stołeczna Policji","woj":null},
    {"kod":"146501","organ":"M. st. Warszawa","pow":"Warszawa","jP":"Komenda Stołeczna Policji","woj":null},
    {"kod":"146502","organ":"Prezydent m. st. Warszawy - Urząd Dzielnicy Bemowo","pow":"Warszawa","jP":"Komenda Stołeczna Policji","woj":null},
    {"kod":"146503","organ":"Prezydent m. st. Warszawy - Urząd Dzielnicy Białołęka","pow":"Warszawa","jP":"Komenda Stołeczna Policji","woj":null},
    {"kod":"146504","organ":"Prezydent m. st. Warszawy - Urząd Dzielnicy Bielany","pow":"Warszawa","jP":"Komenda Stołeczna Policji","woj":null},
    {"kod":"146505","organ":"Prezydent m. st. Warszawy - Urząd Dzielnicy Mokotów","pow":"Warszawa","jP":"Komenda Stołeczna Policji","woj":null},
    {"kod":"146506","organ":"Prezydent m. st. Warszawy - Urząd Dzielnicy Ochota","pow":"Warszawa","jP":"Komenda Stołeczna Policji","woj":null},
    {"kod":"146507","organ":"Prezydent m. st. Warszawy - Urząd Dzielnicy Praga-Południe","pow":"Warszawa","jP":"Komenda Stołeczna Policji","woj":null},
    {"kod":"146508","organ":"Prezydent m. st. Warszawy - Urząd Dzielnicy Praga-Północ","pow":"Warszawa","jP":"Komenda Stołeczna Policji","woj":null},
    {"kod":"146509","organ":"Prezydent m. st. Warszawy - Urząd Dzielnicy Rembertów","pow":"Warszawa","jP":"Komenda Stołeczna Policji","woj":null},
    {"kod":"146510","organ":"Prezydent m. st. Warszawy - Urząd Dzielnicy Śródmieście","pow":"Warszawa","jP":"Komenda Stołeczna Policji","woj":null},
    {"kod":"146511","organ":"Prezydent m. st. Warszawy - Urząd Dzielnicy Targówek","pow":"Warszawa","jP":"Komenda Stołeczna Policji","woj":null},
    {"kod":"146512","organ":"Prezydent m. st. Warszawy - Urząd Dzielnicy Ursus","pow":"Warszawa","jP":"Komenda Stołeczna Policji","woj":null},
    {"kod":"146513","organ":"Prezydent m. st. Warszawy - Urząd Dzielnicy Ursynów","pow":"Warszawa","jP":"Komenda Stołeczna Policji","woj":null},
    {"kod":"146514","organ":"Prezydent m. st. Warszawy - Urząd Dzielnicy Wawer","pow":"Warszawa","jP":"Komenda Stołeczna Policji","woj":null},
    {"kod":"146515","organ":"Prezydent m. st. Warszawy - Urząd Dzielnicy Wesoła","pow":"Warszawa","jP":"Komenda Stołeczna Policji","woj":null},
    {"kod":"146516","organ":"Prezydent m. st. Warszawy - Urząd Dzielnicy Wilanów","pow":"Warszawa","jP":"Komenda Stołeczna Policji","woj":null},
    {"kod":"146517","organ":"Prezydent m. st. Warszawy - Urząd Dzielnicy Włochy","pow":"Warszawa","jP":"Komenda Stołeczna Policji","woj":null},
    {"kod":"146518","organ":"Prezydent m. st. Warszawy - Urząd Dzielnicy Wola","pow":"Warszawa","jP":"Komenda Stołeczna Policji","woj":null},
    {"kod":"146519","organ":"Prezydent m. st. Warszawy - Urząd Dzielnicy Żoliborz","pow":"Warszawa","jP":"Komenda Stołeczna Policji","woj":null},
    {"kod":"0417","organ":"Starosta Wąbrzeski","pow":"wąbrzeski","jP":"KPP w Wąbrzeźnie","woj":null},
    {"kod":"3028","organ":"Starosta Wągrowiecki","pow":"wągrowiecki","jP":"KPP w Wągrowcu","woj":null},
    {"kod":"2215","organ":"Starosta Wejherowski","pow":"wejherowski","jP":"KPP w Wejherowie","woj":null},
    {"kod":"2819","organ":"Starosta Węgorzewski","pow":"węgorzewski","jP":"KPP w Węgorzewie","woj":null},
    {"kod":"1433","organ":"Starosta Węgrowski","pow":"węgrowski","jP":"KPP w Węgrowie","woj":null},
    {"kod":"1219","organ":"Starosta Wielicki","pow":"wielicki","jP":"KPP w Wieliczce","woj":null},
    {"kod":"1017","organ":"Starosta Wieluński","pow":"wieluński","jP":"KPP w Wieluniu","woj":null},
    {"kod":"1018","organ":"Starosta Wieruszowski","pow":"wieruszowski","jP":"KPP w Wieruszowie","woj":null},
    {"kod":"0418","organ":"Starosta Włocławski","pow":"włocławski","jP":"KMP we Włocławku","woj":null},
    {"kod":"0464","organ":"Prezydent Miasta Włocławek","pow":"Włocławek","jP":"KMP we Włocławku","woj":null},
    {"kod":"0619","organ":"Starosta Włodawski","pow":"włodawski","jP":"KPP we Włodawie","woj":null},
    {"kod":"2613","organ":"Starosta Włoszczowski","pow":"włoszczowski","jP":"KPP we Włoszczowie","woj":null},
    {"kod":"2415","organ":"Starosta Wodzisławski","pow":"wodzisławski","jP":"KPP w Wodzisławiu Śląskim","woj":null},
    {"kod":"3029","organ":"Starosta Wolsztyński","pow":"wolsztyński","jP":"KPP w Wolsztynie","woj":null},
    {"kod":"1434","organ":"Starosta Wołomiński","pow":"wołomiński","jP":"KPP w Wołominie","woj":null},
    {"kod":"0222","organ":"Starosta Wołowski","pow":"wołowski","jP":"KPP w Wołowie","woj":null},
    {"kod":"0223","organ":"Starosta Wrocławski","pow":"wrocławski","jP":"KMP we Wrocławiu","woj":null},
    {"kod":"0264","organ":"Prezydent Miasta Wrocław","pow":"Wrocław","jP":"KMP we Wrocławiu","woj":null},
    {"kod":"3030","organ":"Starosta Wrzesiński","pow":"wrzesiński","jP":"KPP we Wrześni","woj":null},
    {"kod":"0812","organ":"Starosta Wschowski","pow":"wschowski","jP":"KPP we Wschowie","woj":null},
    {"kod":"2013","organ":"Starosta Wysokomazowiecki","pow":"wysokomazowiecki","jP":"KPP w  Wysokiem Mazowieckiem","woj":null},
    {"kod":"1435","organ":"Starosta Wyszkowski","pow":"wyszkowski","jP":"KPP w Wyszkowie","woj":null},
    {"kod":"2478","organ":"Prezydent Miasta Zabrze","pow":"Zabrze","jP":"KMP w Zabrzu","woj":null},
    {"kod":"1217","organ":"Starosta Tatrzański","pow":"tatrzański","jP":"KPP w Zakopanem","woj":null},
    {"kod":"2014","organ":"Starosta Zambrowski","pow":"zambrowski","jP":"KPP w Zambrowie","woj":null},
    {"kod":"0620","organ":"Starosta Zamojski","pow":"zamojski","jP":"KMP w Zamościu","woj":null},
    {"kod":"0664","organ":"Prezydent Miasta Zamość","pow":"Zamość","jP":"KMP w Zamościu","woj":null},
    {"kod":"2416","organ":"Starosta Zawierciański","pow":"zawierciański","jP":"KPP w Zawierciu","woj":null},
    {"kod":"0224","organ":"Starosta Ząbkowicki","pow":"ząbkowicki","jP":"KPP w Ząbkowicach Śląskich","woj":null},
    {"kod":"1019","organ":"Starosta Zduńskowolski","pow":"zduńskowolski","jP":"KPP w Zduńskiej Woli","woj":null},
    {"kod":"1020","organ":"Starosta Zgierski","pow":"zgierski","jP":"KPP w Zgierzu","woj":null},
    {"kod":"0225","organ":"Starosta Zgorzelecki","pow":"zgorzelecki","jP":"KPP w Zgorzelcu","woj":null},
    {"kod":"0809","organ":"Starosta Zielonogórski","pow":"zielonogórski","jP":"KMP w Zielonej Górze","woj":null},
    {"kod":"0862","organ":"Prezydent Miasta Zielona Góra","pow":"Zielona Góra","jP":"KMP w Zielonej Górze","woj":null},
    {"kod":"0226","organ":"Starosta Złotoryjski","pow":"złotoryjski","jP":"KPP w Złotoryi","woj":null},
    {"kod":"3031","organ":"Starosta Złotowski","pow":"złotowski","jP":"KPP w Złotowie","woj":null},
    {"kod":"1436","organ":"Starosta Zwoleński","pow":"zwoleński","jP":"KPP w Zwoleniu","woj":null},
    {"kod":"0810","organ":"Starosta Żagański","pow":"żagański","jP":"KPP w Żaganiu","woj":null},
    {"kod":"0811","organ":"Starosta Żarski","pow":"żarski","jP":"KPP w Żarach","woj":null},
    {"kod":"0419","organ":"Starosta Żniński","pow":"żniński","jP":"KPP w Żninie","woj":null},
    {"kod":"2479","organ":"Prezydent Miasta Żory","pow":"Żory","jP":"KMP w Żorach","woj":null},
    {"kod":"1437","organ":"Starosta Żuromiński","pow":"żuromiński","jP":"KPP w Żurominie","woj":null},
    {"kod":"1438","organ":"Starosta Żyrardowski","pow":"żyrardowski","jP":"KPP w Żyrardowie","woj":null},
    {"kod":"2417","organ":"Starosta Żywiecki","pow":"żywiecki","jP":"KPP w Żywcu","woj":null},
    {"kod":"2261","organ":"Prezydent Miasta Gdańsk","pow":"Gdańsk","jP":"KMP w Gdańsku","woj":null},
    {"kod":"2262","organ":"Prezydent Miasta Gdynia","pow":"Gdynia","jP":"KMP w Gdyni","woj":null},
    {"kod":"3203","organ":"Starosta Drawski","pow":"drawski","jP":"KPP Drawsko Pomorskie","woj":null},
    {"kod":"2861","organ":"Prezydent Miasta Elbląg","pow":"elbląski","jP":"KMP w Elblągu","woj":null},
    {"kod":"2465","organ":"Prezydent Miasta Dąbrowa Górnicza","pow":"Dąbrowa Górnicza","jP":"KMP w Dąbrowie Górniczej","woj":null},
    {"kod":"1204","organ":"","pow":"dąbrowski ","jP":"KPP w Dąbrowie Tarnowskiej","woj":null},
    {"kod":"2803","organ":"","pow":"działdowski","jP":"KPP w Działdowie","woj":null},
    {"kod":"2805","organ":"","pow":"ełcki","jP":"KPP w Ełku","woj":null},
    {"kod":"2806","organ":"","pow":"giżycki","jP":"KPP W Giżycku","woj":null},
    {"kod":"2203","organ":"","pow":"człuchowski","jP":"KPP w Człuchowie","woj":null},
    {"kod":"1803","organ":"","pow":"dębicki","jP":"KPP w Dębica","woj":null},
    {"kod":"1403","organ":"","pow":"garwoliński","jP":"KPP w Garwolinie","woj":null},
    {"kod":"0603","organ":"","pow":"chełmiński","jP":"KPP w Chełmnie","woj":null},
    {"kod":"0202","organ":"","pow":"dzierżoniowski","jP":"KPP w Dzierżoniowie","woj":null}]